scrouter/__init__.py
scrouter/__main__.py
scrouter/agent.py
scrouter/scratch_api.py
scrouter/worker.py
ky.scrouter-1.0.post1.dist-info/LICENSE
ky.scrouter-1.0.post1.dist-info/WHEEL
ky.scrouter-1.0.post1.dist-info/METADATA
ky.scrouter-1.0.post1.dist-info/RECORD
