Metadata-Version: 2.1
Name: ky.scrouter
Version: 1.0.post1
Summary: A tool that looks for relations between users
License: MIT
Keywords: scratch,routing,ky,procybit
Author: Leon "Procybit" Shepelev
Author-email: kyleusnaff@gmail.com
Requires-Python: >=3.8,<4.0
Classifier: License :: OSI Approved :: MIT License
Classifier: Programming Language :: Python :: 3
Classifier: Programming Language :: Python :: 3.10
Classifier: Programming Language :: Python :: 3.8
Classifier: Programming Language :: Python :: 3.9
Requires-Dist: requests (>=2.28,<2.29)
